poetry_plugin_export/__init__.py
poetry_plugin_export/command.py
poetry_plugin_export/exporter.py
poetry_plugin_export/plugins.py
poetry_plugin_export/walker.py
poetry_plugin_export-1.1.1.dist-info/entry_points.txt
poetry_plugin_export-1.1.1.dist-info/LICENSE
poetry_plugin_export-1.1.1.dist-info/WHEEL
poetry_plugin_export-1.1.1.dist-info/METADATA
poetry_plugin_export-1.1.1.dist-info/RECORD
