Metadata-Version: 2.1
Name: poetry-plugin-export
Version: 1.1.1
Summary: Poetry plugin to export the dependencies to various formats
Home-page: https://python-poetry.org/
License: MIT
Author: Sébastien Eustace
Author-email: sebastien@eustace.io
Requires-Python: >=3.7,<4.0
Classifier: License :: OSI Approved :: MIT License
Classifier: Programming Language :: Python :: 3
Classifier: Programming Language :: Python :: 3.7
Classifier: Programming Language :: Python :: 3.8
Classifier: Programming Language :: Python :: 3.9
Classifier: Programming Language :: Python :: 3.10
Requires-Dist: poetry (>=1.2.0,<2.0.0)
Requires-Dist: poetry-core (>=1.1.0,<2.0.0)
Project-URL: Repository, https://github.com/python-poetry/poetry-plugin-export
